README
setup.py
srt_shift.py
srt_shift.egg-info/PKG-INFO
srt_shift.egg-info/SOURCES.txt
srt_shift.egg-info/dependency_links.txt
srt_shift.egg-info/entry_points.txt
srt_shift.egg-info/not-zip-safe
srt_shift.egg-info/top_level.txt