Metadata-Version: 1.0
Name: srt-shift
Version: 0.2
Summary: For fixing out-of-sync .srt subtitle files.
Home-page: UNKNOWN
Author: Adeel Ahmad Khan
Author-email: adeel2@umbc.edu
License: UNKNOWN
Platform: UNKNOWN
Classifier: Development Status :: 4 - Beta
Classifier: Environment :: Console
Classifier: License :: OSI Approved :: BSD License
Classifier: Natural Language :: English
Classifier: Operating System :: POSIX
Classifier: Topic :: Utilities
